{"volume":55309,"metadata":{"fileName":"ship0324.htm","file":"d:\\temp\\data\\ship\\deanfiles\\ship0324.htm","htmlFile":"d:\\temp\\data\\ship\\deanfiles\\ship0324.htm","raw":"<HTML>\n<HEAD>\n<META Name=\"Generator\" Content=\"Lotus Word Pro\">\n<TITLE>Pesago Express<\/TITLE>\n<\/HEAD>\n<BODY BGCOLOR=\"#000000\" LINK=\"#6699FF\" VLINK=\"#FFFFFF\" TEXT=\"#FFCE09\">\n\n<B>\n<FONT size=+1>Pesago Express<\/FONT><\/B>  (Civilian Starship)<P>\n\n<P>\n\n     The Pesago is the low end freighter meeting a maneuver-2, jump-3\nrequirement. It has an operating cost of 1212Cr per ton per fortnight (730 if\nit scoops its own fuel). Although it cannot compete on jump-1 runs, express\nfreight contracts over a jump-3 usually give it a tidy profit margin.<P>\n\n    There is no surplus power for any armament. If armament is desired a\nsupplementary power suply must be added or else forgo the maneuver-2\npreformance.<P>\n\n<P>\n\n<TABLE border=1>\n\n<TR><TD>CraftID:\n<TD>Pesago Express Freighter, TL15, MCr802.346\n<\/TR>\n\n<TR><TD>Hull:\n<TD>3688\/9219, Disp=4097t, Config=4SL, Armour=40G,<P>\n         Loaded=58050, Unloaded=13480\n<\/TR>\n\n<TR><TD>Power:\n<TD>11\/28, Fusion=3074MW, Duration=30\/90\n<\/TR>\n\n<TR><TD>Loco:\n<TD>184\/461, Maneuver=2, 148\/369, Jump=3, Cruise=750kph,\nMax=1000kph, Agility=0\n<\/TR>\n\n<TR><TD>Comm:\n<TD>Radio=System\n<\/TR>\n\n<TR><TD>Sensors:\n<TD>EMS Active (Planetary), EMS Passive (Substellar),\nActObjScan=Diff, ActObjPin=Diff, PassEngScan=Rout\n<\/TR>\n\n<TR><TD>Off:\n<TD><PRE>Hardpoints=40\n<\/PRE><\/TR>\n\n<TR><TD>Def:\n<TD><PRE>+3\n<\/PRE><\/TR>\n\n<TR><TD>Control:\n<TD>Computer Mod3*3, 74*LargeHoloDisp, 17*HoloLink\n<\/TR>\n\n<TR><TD>Accom:\n<TD>Crew=19 (6 bridge, 11 engineer, 2 command), Staterooms=19,\nEnv=all\n<\/TR>\n\n<TR><TD>Other:\n<TD>Fuel=901t, Cargo=2400t, Fuel Scoops, Fuel Purefier(24h),\nObjSize=Average, EmmLevel=Moderate<\/TABLE>\n<P>\n\n<P>\n\n<IMG src=\"ship0324_00.png\"\/>\n<P>\nAuthor: J.Grant\n<\/BODY>\n<\/HTML>\n","dir":"d:\\temp\\data\\ship\\deanfiles","baseName":"ship0324"},"configuration":4,"items":[{"volume":2765.45,"number":0,"type":2},{"volume":2212.36,"number":0,"type":3},{"volume":165.0,"number":0,"type":4},{"volume":32400.0,"number":0,"type":7},{"volume":12163.5,"number":0,"type":5},{"volume":54.0,"number":19,"type":11}]}